LICENSE
README.md
setup.py
logger_builder/__init__.py
logger_builder/formatter.py
logger_builder/logger_builder.py
logger_builder.egg-info/PKG-INFO
logger_builder.egg-info/SOURCES.txt
logger_builder.egg-info/dependency_links.txt
logger_builder.egg-info/top_level.txt
logger_builder/handler/__init__.py
logger_builder/handler/http.py
logger_builder/handler/memory.py
logger_builder/handler/factory/__init__.py
logger_builder/handler/factory/abstract.py
logger_builder/handler/factory/file.py
logger_builder/handler/factory/memory.py
logger_builder/handler/factory/stream.py