Metadata-Version: 2.1
Name: logger-builder
Version: 0.0.2
Summary: Logger builder to simplify creation of the loggers
Home-page: https://github.com/LudwikBielczynski/logger_builder.git
Author: Ludwik Bielczynski
Author-email: ludwik.bielczynski@gmail.com
License: UNKNOWN
Platform: UNKNOWN
Classifier: Programming Language :: Python :: 3
Classifier: License :: OSI Approved :: MIT License
Classifier: Operating System :: OS Independent
Requires-Python: >=3.6
